[{"id":1,"o":1457,"text":"","url":"1457.htm","node":"0","leaf":true,"hidden":true},{"id":2,"o":4656,"text":"Disclaimer and Copyright","url":"4656.htm","node":"1","leaf":true},{"id":3,"o":14867,"text":"Convergent Billing Overview","url":"14867.htm","node":"2","children":[]},{"id":4,"o":1461,"text":"Using the Help","url":"1461.htm","node":"3","leaf":true},{"id":5,"o":4501,"text":"Reference Information","url":"4501.htm","node":"4","children":[]},{"id":6,"o":1732,"text":"Convergent Billing Forms","url":"1732.htm","node":"5","children":[]},{"id":7,"o":1511,"text":"How Do I - General Operations","url":"1511.htm","node":"6","children":[]},{"id":8,"o":4111,"text":"How Do I - Customer Care Tasks","url":"4111.htm","node":"7","children":[]},{"id":9,"o":4223,"text":"How Do I - Customer Care Configuration Tasks","url":"4223.htm","node":"8","children":[]},{"id":10,"o":4291,"text":"How Do I - Product Configuration Tasks","url":"4291.htm","node":"9","children":[]},{"id":11,"o":11242,"text":"How Do I - Financial Configuration Tasks","url":"11242.htm","node":"10","children":[]},{"id":12,"o":4371,"text":"How Do I - Operations","url":"4371.htm","node":"11","children":[]},{"id":13,"o":4415,"text":"How Do I - Security Tasks","url":"4415.htm","node":"12","children":[]},{"id":14,"o":4383,"text":"How Do I - Operations - Reports","url":"4383.htm","node":"13","children":[]},{"id":15,"o":4411,"text":"How Do I - Operations - Bill Runs","url":"4411.htm","node":"14","children":[]},{"id":16,"o":4447,"text":"How Do I - System Administration Tasks","url":"4447.htm","node":"15","children":[]},{"id":17,"o":55357,"text":"How Do I - System Integration Tasks","url":"55357.htm","node":"16","children":[]},{"id":18,"o":14827,"text":"Glossary of Terms","url":"14827.htm","node":"17","children":[]}]